[{"bookId":"A","bookName":"Memorials of the Faithful","files":["abd-mf-en.html"],"meta":{"fileName":"2b96dd6fbcdf04bcea4f1a809cdac225","toc":[{"text":"Nabíl-i-Akbar","number":"1","id":"para_3"},{"text":"Ismu’lláhu’l-Asdaq","number":"2","id":"para_25"},{"text":"Mullá ‘Alí-Akbar","number":"3","id":"para_38"},{"text":"Shaykh Salmán","number":"4","id":"para_50"},{"text":"Mírzá Muḥammad-‘Alí, the Afnán","number":"5","id":"para_77"},{"text":"Ḥájí Mírzá Ḥasan, the Afnán","number":"6","id":"para_94"},{"text":"Muḥammad-‘Alíy-i-Iṣfahání","number":"7","id":"para_103"},{"text":"‘Abdu’ṣ-Ṣáliḥ, the Gardener","number":"8","id":"para_113"},{"text":"Ustád Ismá‘íl","number":"9","id":"para_122"},{"text":"Nabíl-i-Zarandí","number":"10","id":"para_130"},{"text":"Darvísh Ṣidq-‘Alí","number":"11","id":"para_144"},{"text":"Áqá Mírzá Maḥmúd and Áqá Riḍá","number":"12","id":"para_154"},{"text":"Pidar-Ján of Qazvín","number":"13","id":"para_163"},{"text":"Shaykh Ṣádiq-i-Yazdí","number":"14","id":"para_169"},{"text":"Sháh-Muḥammad-Amín","number":"15","id":"para_178"},{"text":"Mashhadí Faṭṭáḥ","number":"16","id":"para_190"},{"text":"Nabíl of Qá’in","number":"17","id":"para_196"},{"text":"Siyyid Muḥammad-Taqí Manshádí","number":"18","id":"para_215"},{"text":"Muḥammad-‘Alí Ṣabbáq of Yazd","number":"19","id":"para_224"},{"text":"‘Abdu’l-Ghaffár of Iṣfahán","number":"20","id":"para_231"},{"text":"‘Alí Najaf-Ábádí","number":"21","id":"para_238"},{"text":"Mashhadí Ḥusayn and Mashhadí Muḥammad-i-Ádhirbáyjání","number":"22","id":"para_243"},{"text":"Ḥájí ‘Abdu’r-Raḥím-i-Yazdí","number":"23","id":"para_248"},{"text":"Ḥájí ‘Abdu’lláh Najaf-Ábádí","number":"24","id":"para_259"},{"text":"Muḥammad-Hádíy-i-Ṣaḥḥáf","number":"25","id":"para_264"},{"text":"Mírzá Muḥammad-Qulí","number":"26","id":"para_279"},{"text":"Ustád Báqir and Ustád Aḥmad","number":"27","id":"para_285"},{"text":"Muḥammad Ḥaná-Sáb","number":"28","id":"para_291"},{"text":"Ḥájí Faraju’lláh Tafríshí","number":"29","id":"para_297"},{"text":"Áqá Ibráhím-i-Iṣfahání and His Brothers","number":"30","id":"para_302"},{"text":"Áqá Muḥammad-Ibráhím","number":"31","id":"para_313"},{"text":"Zaynu’l-‘Ábidín Yazdí","number":"32","id":"para_319"},{"text":"Ḥájí Mullá Mihdíy-i-Yazdí","number":"33","id":"para_325"},{"text":"His Eminence Kalím (Mírzá Músá)","number":"34","id":"para_331"},{"text":"Ḥájí Muḥammad Khán","number":"35","id":"para_346"},{"text":"Áqá Muḥammad-Ibráhím Amír","number":"36","id":"para_356"},{"text":"Mírzá Mihdíy-i-Káshání","number":"37","id":"para_360"},{"text":"Mishkín-Qalam","number":"38","id":"para_369"},{"text":"Ustád ‘Alí-Akbar-i-Najjár","number":"39","id":"para_381"},{"text":"Shaykh ‘Alí-Akbar-i-Mázgání","number":"40","id":"para_388"},{"text":"Mírzá Muḥammad, the Servant at the Travelers’ Hospice","number":"41","id":"para_394"},{"text":"Mírzá Muḥammad-i-Vakíl","number":"42","id":"para_400"},{"text":"Ḥájí Muḥammad-Riḍáy-i-Shírází","number":"43","id":"para_422"},{"text":"Ḥusayn Effendi Tabrízí","number":"44","id":"para_428"},{"text":"Jamshíd-i-Gurjí","number":"45","id":"para_434"},{"text":"Ḥájí Ja‘far-i-Tabrízí and His Brothers","number":"46","id":"para_442"},{"text":"Ḥájí Mírzá Muḥammad-Taqí, the Afnán","number":"47","id":"para_452"},{"text":"‘Abdu’lláh Baghdádí","number":"48","id":"para_462"},{"text":"Muḥammad-Muṣṭafá Baghdádí","number":"49","id":"para_468"},{"text":"Sulaymán Khán-i-Tunukábání","number":"50","id":"para_479"},{"text":"‘Abdu’r-Raḥmán, the Coppersmith","number":"51","id":"para_492"},{"text":"Muḥammad-Ibráhím-i-Tabrízí","number":"52","id":"para_497"},{"text":"Muḥammad-‘Alíy-i-Ardikání","number":"53","id":"para_502"},{"text":"Ḥájí Áqáy-i-Tabrízí","number":"54","id":"para_507"},{"text":"Ustád Qulám-‘Alíy-i-Najjár","number":"55","id":"para_512"},{"text":"Jináb-i-Muníb, upon him be the Glory of the All-Glorious","number":"56","id":"para_518"},{"text":"Mírzá Muṣṭafá Naráqí","number":"57","id":"para_529"},{"text":"Zaynu’l-Muqarrabín","number":"58","id":"para_539"},{"text":"‘Aẓím-i-Tafríshí","number":"59","id":"para_550"},{"text":"Mírzá Ja‘far-i-Yazdí","number":"60","id":"para_558"},{"text":"Ḥusayn-Áqáy-i-Tabrízí","number":"61","id":"para_567"},{"text":"Ḥájí ‘Alí-‘Askar-i-Tabrízí","number":"62","id":"para_574"},{"text":"Áqá ‘Alíy-i-Qazvíní","number":"63","id":"para_589"},{"text":"Áqá Muḥammad-Báqir and Áqá Muḥammad-Ismá‘íl, the Tailor","number":"64","id":"para_599"},{"text":"Abu’l-Qásim of Sulṭán-Ábád","number":"65","id":"para_613"},{"text":"Áqá Faraj","number":"66","id":"para_617"},{"text":"The Consort of the King of Martyrs","number":"67","id":"para_623"},{"text":"Shamsu’ḍ-Ḍuḥá","number":"68","id":"para_642"},{"text":"Ṭáhirih","number":"69","id":"para_668"}],"authors":["‘Abdu’l-Bahá"],"wordsCount":57646,"sourceURL":"http://reference.bahai.org/download/mf-en-doc.zip","paragraphsNumber":832,"name":"Memorials of the Faithful","weight":300,"totalCharacters":"55118","description":"These are brief stories of people's lives; various people who all met Baha'u'llah at one time or another during His lengthy incarceration in the Akka (Acre) area and who were dedicated followers. Some stories are only a couple of pages long; the longest ones are 14 and 15 pages long; altogether there are 69 stories in about 200 pages. As usual the author (Abdu'l-Baha) does not dwell on any negative aspects of someone's personality but only the good seen in them. Especially moving are His invocations of blessings on the person (all of whom had passed away) at the close of each story: very brief prayers in heartfelt, moving language also indicating what a great spiritual station He felt each one had attained. And these are all stories about what true religion is supposed to be: they are all in the language of love. Love, sacrifice, humility, are some of the qualities reflected over and over again, though each story is unique.","readingTime":24720000,"title":"Memorials of the Faithful","acronym":"MF","audio":"true","subject":"Bahá’í","author":"‘Abdu’l-Bahá","publisher":"FFA","publisher-url":"firm-foundation.org","original-language":"en","source":"US Bah&aacute;&#8217;&iacute; Publishing Trust, 1971 edition","abbreviationTitle":"mf","abbreviationAuthor":"abd","priority":"300","religion":"Bahaism","category":"Bahá’í","language":"en","coverFile":"AbdulBaha-Memorials-of-the-Faithful.png","cover":"697b98126e59958015546ecb5d93fd40"},"globalId":"2b96dd6fbcdf04bcea4f1a809cdac225"}]